{
    "sha512_hash": "3f024e5400ec354387bb05b41a20077908ea11a8cee4dd41e472d18acbf5d64879a2f080f98d3cd55f350498f3eb826d3b0faa060c256861a8c155b08cf6cf24",
    "wilson_score": 0.9622669784316855,
    "thumbnails_generated": true,
    "mime_type": "image/png",
    "uploader_id": 228449,
    "source_url": "http://avchonline.deviantart.com/art/Coco-as-Alice-in-wonderland-2-428286173",
    "size": 2940276,
    "tags": [
        "clothes",
        "crossover",
        "disney",
        "dress",
        "giant pony",
        "giantess",
        "macro",
        "pony",
        "safe",
        "solo",
        "g4",
        "coco pommel",
        "alice in wonderland",
        "puffy sleeves",
        "female",
        "giant/mega coco pommel",
        "earth pony",
        "giant/macro earth pony",
        "artist:avchonline",
        "bloomers",
        "blushing",
        "bow"
    ],
    "representations": {
        "full": "https://derpicdn.net/img/view/2014/1/21/530730.png",
        "small": "https://derpicdn.net/img/2014/1/21/530730/small.png",
        "thumb_tiny": "https://derpicdn.net/img/2014/1/21/530730/thumb_tiny.png",
        "thumb_small": "https://derpicdn.net/img/2014/1/21/530730/thumb_small.png",
        "thumb": "https://derpicdn.net/img/2014/1/21/530730/thumb.png",
        "medium": "https://derpicdn.net/img/2014/1/21/530730/medium.png",
        "large": "https://derpicdn.net/img/2014/1/21/530730/large.png",
        "tall": "https://derpicdn.net/img/2014/1/21/530730/tall.png"
    },
    "view_url": "https://derpicdn.net/img/view/2014/1/21/530730__safe_artist-colon-avchonline_coco+pommel_earth+pony_pony_g4_alice+in+wonderland_bloomers_blushing_bow_clothes_crossover_disney_dress_female_giant+pony_.png",
    "orig_sha512_hash": "3f024e5400ec354387bb05b41a20077908ea11a8cee4dd41e472d18acbf5d64879a2f080f98d3cd55f350498f3eb826d3b0faa060c256861a8c155b08cf6cf24",
    "deletion_reason": null,
    "created_at": "2014-01-21T22:05:47Z",
    "width": 2500,
    "aspect_ratio": 0.9615384615384616,
    "source_urls": [
        "http://avchonline.deviantart.com/art/Coco-as-Alice-in-wonderland-2-428286173"
    ],
    "hidden_from_users": false,
    "description": "\n> ohoh! our little coco alice is being naughty and adorable again~ she just drink the thing on the table and become a little tiny pony~yet she than realize that she left the key on the table, where it too high for her to get, so she eat a little cookie have the word \"Eat me\"on it, \n> and than all of a sudden, she started to grow up and become so big that almost stuck in to the whole room, poor and cute little coco than start to cry, i guess i will drew the part her cring, \n> \n> and hope you enjoy it, maybe i can get to the part that she stuck in the rabbit house. \n> \n> Sean\n",
    "faves": 152,
    "tag_count": 22,
    "duplicate_of": null,
    "animated": false,
    "comment_count": 16,
    "tag_ids": [
        23269,
        24046,
        25230,
        25783,
        28661,
        28666,
        33620,
        38185,
        40482,
        42350,
        28260,
        192411,
        662,
        222383,
        27141,
        507915,
        26029,
        506177,
        2921,
        21212,
        21297,
        21498
    ],
    "processed": true,
    "spoilered": false,
    "height": 2600,
    "score": 217,
    "duration": 0.04,
    "upvotes": 218,
    "format": "png",
    "uploader": "And Brother I Hurt People",
    "id": 530730,
    "name": "23_05_47_759_file",
    "downvotes": 1,
    "intensities": {
        "nw": 127.753567,
        "ne": 47.039162,
        "sw": 148.920996,
        "se": 104.888948
    },
    "updated_at": "2023-07-24T00:48:43Z",
    "orig_size": 2940276,
    "first_seen_at": "2014-01-21T22:05:47Z",
    "filename": "530730__safe_artist-colon-avchonline_coco+pommel_earth+pony_pony_g4_alice+in+wonderland_bloomers_blushing_bow_clothes_crossover_disney_dress_female_giant+pony_",
    "extension": "png",
    "search_tags": "artist:avchonline",
    "date": "2014-01-21 22:05:47",
    "category": "derpibooru",
    "subcategory": "search"
}
